[
  { "Id": "01", "State": "HN" },
  { "Id": "02", "State": "HG" },
  { "Id": "04", "State": "CB" },
  { "Id": "06", "State": "BK" },
  { "Id": "08", "State": "TQ" },
  { "Id": "10", "State": "LC" },
  { "Id": "11", "State": "DB" },
  { "Id": "12", "State": "LC" },
  { "Id": "14", "State": "SL" },
  { "Id": "15", "State": "YB" },
  { "Id": "17", "State": "HB" },
  { "Id": "19", "State": "TN" },
  { "Id": "20", "State": "LS" },
  { "Id": "24", "State": "QN" },
  { "Id": "26", "State": "BG" },
  { "Id": "27", "State": "PT" },
  { "Id": "30", "State": "VP" },
  { "Id": "31", "State": "HP" },
  { "Id": "33", "State": "HY" },
  { "Id": "34", "State": "TB" },
  { "Id": "35", "State": "HN" },
  { "Id": "36", "State": "ND" },
  { "Id": "37", "State": "NB" },
  { "Id": "38", "State": "TH" },
  { "Id": "40", "State": "NA" },
  { "Id": "42", "State": "HT" },
  { "Id": "44", "State": "QB" },
  { "Id": "45", "State": "QT" },
  { "Id": "46", "State": "TTH" },
  { "Id": "48", "State": "DN" },
  { "Id": "49", "State": "QN" },
  { "Id": "51", "State": "QNg" },
  { "Id": "52", "State": "BD" },
  { "Id": "54", "State": "PY" },
  { "Id": "56", "State": "KH" },
  { "Id": "58", "State": "NT" },
  { "Id": "60", "State": "BT" },
  { "Id": "62", "State": "KT" },
  { "Id": "64", "State": "GL" },
  { "Id": "66", "State": "DL" },
  { "Id": "67", "State": "DNong" },
  { "Id": "68", "State": "LD" },
  { "Id": "70", "State": "BP" },
  { "Id": "72", "State": "TN" },
  { "Id": "74", "State": "BD" },
  { "Id": "75", "State": "ĐN" },
  { "Id": "77", "State": "BRVT" },
  { "Id": "79", "State": "HCM" },
  { "Id": "80", "State": "LA" },
  { "Id": "82", "State": "TG" },
  { "Id": "83", "State": "BTre" },
  { "Id": "84", "State": "TV" },
  { "Id": "86", "State": "VL" },
  { "Id": "87", "State": "DT" },
  { "Id": "89", "State": "AG" },
  { "Id": "91", "State": "KG" },
  { "Id": "92", "State": "CT" },
  { "Id": "93", "State": "HG" },
  { "Id": "94", "State": "ST" },
  { "Id": "95", "State": "BL" },
  { "Id": "96", "State": "CM" }
]